Metadata-Version: 2.1
Name: datasette-sqlite-debug-authorizer
Version: 0.1.1
Summary: Debug SQLite authorizer calls
Author: Simon Willison
License: Apache-2.0
Project-URL: Homepage, https://github.com/simonw/datasette-sqlite-debug-authorizer
Project-URL: Changelog, https://github.com/simonw/datasette-sqlite-debug-authorizer/releases
Project-URL: Issues, https://github.com/simonw/datasette-sqlite-debug-authorizer/issues
Project-URL: CI, https://github.com/simonw/datasette-sqlite-debug-authorizer/actions
Classifier: Framework :: Datasette
Classifier: License :: OSI Approved :: Apache Software License
Requires-Python: >=3.8
License-File: LICENSE
Requires-Dist: datasette
Provides-Extra: test
Requires-Dist: pytest ; extra == 'test'
Requires-Dist: pytest-asyncio ; extra == 'test'
